{
    "js": [
        "js/dataTables.bootstrap4.js",
        "js/dataTables.bootstrap4.min.js",
        "js/dataTables.bootstrap4.min.mjs",
        "js/dataTables.bootstrap4.mjs"
    ],
    "css": [
        "css/dataTables.bootstrap4.css",
        "css/dataTables.bootstrap4.min.css"
    ],
    "types": [
        "types/dataTables.bootstrap4.d.ts"
    ],
    "src-repo": "http://github.com/DataTables/DataTablesSrc",
    "last-tag": "2.3.0",
    "last-sync": "628edf013b20d376667768f2ce999b8ecb9a60ad"
}